MANIFEST.in
README.md
requirements.txt
setup.py
braspag/__init__.py
braspag/core.py
braspag/exceptions.py
braspag/utils.py
braspag/version.py
braspag.egg-info/PKG-INFO
braspag.egg-info/SOURCES.txt
braspag.egg-info/dependency_links.txt
braspag.egg-info/not-zip-safe
braspag.egg-info/requires.txt
braspag.egg-info/top_level.txt
braspag/templates/authorize.xml
braspag/templates/base.xml