Metadata-Version: 1.0
Name: braspag
Version: 0.2.1
Summary: Python library to consume Braspag SOAP Web services
Home-page: https://github.com/TracyWebTech/braspag
Author: Sergio Oliveira
Author-email: sergio@tracy.com.br
License: UNKNOWN
Platform: UNKNOWN
